jandd.sphinxext.mac-0.1.0-nspkg.pth
jandd/sphinxext/mac.py
jandd.sphinxext.mac-0.1.0.dist-info/DESCRIPTION.rst
jandd.sphinxext.mac-0.1.0.dist-info/METADATA
jandd.sphinxext.mac-0.1.0.dist-info/RECORD
jandd.sphinxext.mac-0.1.0.dist-info/WHEEL
jandd.sphinxext.mac-0.1.0.dist-info/metadata.json
jandd.sphinxext.mac-0.1.0.dist-info/namespace_packages.txt
jandd.sphinxext.mac-0.1.0.dist-info/top_level.txt
