Metadata-Version: 2.0
Name: jandd.sphinxext.mac
Version: 0.1.0
Summary: MAC address extension for Sphinx
Home-page: UNKNOWN
Author: Jan Dittberner
Author-email: jan@dittberner.info
License: GPLv3+
Keywords: sphinx extension MAC
Platform: any
Classifier: Development Status :: 3 - Alpha
Classifier: Framework :: Sphinx :: Extension
Classifier: License :: OSI Approved :: GNU General Public License v3 or later (GPLv3+)
Classifier: Programming Language :: Python :: 3
Classifier: Topic :: Documentation
Classifier: Topic :: Internet
Requires-Dist: Sphinx (>=1.4)
